genai_monitor/__init__.py
genai_monitor/__version__.py
genai_monitor/config.py
genai_monitor/database_versioning.py
genai_monitor/dependencies.py
genai_monitor/py.typed
genai_monitor/auto/__init__.py
genai_monitor/common/__init__.py
genai_monitor/common/errors.py
genai_monitor/common/types.py
genai_monitor/common/utils.py
genai_monitor/common/structures/__init__.py
genai_monitor/common/structures/data.py
genai_monitor/db/__init__.py
genai_monitor/db/config.py
genai_monitor/db/manager.py
genai_monitor/db/schemas/__init__.py
genai_monitor/db/schemas/base.py
genai_monitor/db/schemas/tables.py
genai_monitor/injectors/__init__.py
genai_monitor/injectors/containers.py
genai_monitor/injectors/registry.py
genai_monitor/injectors/wrapper.py
genai_monitor/query/__init__.py
genai_monitor/query/api.py
genai_monitor/registration/__init__.py
genai_monitor/registration/api.py
genai_monitor/registration/auto.py
genai_monitor/registration/collection.py
genai_monitor/registration/utils.py
genai_monitor/registration/data/diffusers.json
genai_monitor/registration/data/evaluators.json
genai_monitor/registration/data/litellm.json
genai_monitor/registration/data/providers.json
genai_monitor/registration/data/transformers.json
genai_monitor/registration/data/transformers2.json
genai_monitor/static/constants.py
genai_monitor/static/extras.py
genai_monitor/static/fields.py
genai_monitor/structures/__init__.py
genai_monitor/structures/persistency_manager.py
genai_monitor/structures/runtime_manager.py
genai_monitor/structures/conditioning_parsers/__init__.py
genai_monitor/structures/conditioning_parsers/base.py
genai_monitor/structures/conditioning_parsers/litellm.py
genai_monitor/structures/conditioning_parsers/openai.py
genai_monitor/structures/conditioning_parsers/seed_types.py
genai_monitor/structures/conditioning_parsers/stable_diffusion.py
genai_monitor/structures/conditioning_parsers/transformers_text_generation.py
genai_monitor/structures/output_parsers/__init__.py
genai_monitor-0.0.1.dist-info/licenses/LICENSE
genai_monitor-0.0.1.dist-info/METADATA
genai_monitor-0.0.1.dist-info/WHEEL
genai_monitor-0.0.1.dist-info/top_level.txt
genai_monitor-0.0.1.dist-info/RECORD
