Metadata-Version: 2.4
Name: genai-monitor
Version: 0.0.1
Summary: Observability for Generative AI
Author-email: "deepsense.ai" <contact@deepsense.ai>
License: MIT
Keywords: Large Language Models,LLMs,Generative AI,GenAI
Classifier: Development Status :: 4 - Beta
Classifier: Intended Audience :: Developers
Classifier: Topic :: Software Development :: Libraries
Classifier: License :: OSI Approved :: MIT License
Classifier: Programming Language :: Python :: 3.10
Classifier: Programming Language :: Python :: 3.11
Classifier: Programming Language :: Python :: 3.12
Requires-Python: >=3.10
License-File: LICENSE
Requires-Dist: sqlalchemy>=2.0.35
Requires-Dist: sqlalchemy-mixins>=2.0.5
Requires-Dist: loguru>=0.7.2
Requires-Dist: attrs>=24.2.0
Requires-Dist: cattrs>=24.1.2
Requires-Dist: pydantic-settings>=2.6.1
Requires-Dist: dependency_injector>=4.45.0
Provides-Extra: diffusers
Requires-Dist: diffusers>=0.31.0; extra == "diffusers"
Requires-Dist: transformers>=4.46.2; extra == "diffusers"
Requires-Dist: torch>=1.10.0; extra == "diffusers"
Requires-Dist: sentencepiece>=0.1.96; extra == "diffusers"
Provides-Extra: transformers
Requires-Dist: transformers>=4.46.2; extra == "transformers"
Requires-Dist: torch>=1.10.0; extra == "transformers"
Provides-Extra: openai
Requires-Dist: openai>=1.55.0; extra == "openai"
Provides-Extra: litellm
Requires-Dist: litellm>=1.60.2; extra == "litellm"
Dynamic: license-file
